jaeger/__init__.py
jaeger/__main__.py
jaeger/alerts.py
jaeger/can.py
jaeger/chiller.py
jaeger/exceptions.py
jaeger/fps.py
jaeger/fvc.py
jaeger/ieb.py
jaeger/kaiju.py
jaeger/maskbits.py
jaeger/plotting.py
jaeger/positioner.py
jaeger/testing.py
jaeger/actor/__init__.py
jaeger/actor/actor.py
jaeger/actor/commands/__init__.py
jaeger/actor/commands/alerts.py
jaeger/actor/commands/calibrations.py
jaeger/actor/commands/can.py
jaeger/actor/commands/chiller.py
jaeger/actor/commands/configuration.py
jaeger/actor/commands/debug.py
jaeger/actor/commands/disable.py
jaeger/actor/commands/fvc.py
jaeger/actor/commands/home.py
jaeger/actor/commands/ieb.py
jaeger/actor/commands/pollers.py
jaeger/actor/commands/positioner.py
jaeger/actor/commands/power.py
jaeger/actor/commands/snapshot.py
jaeger/actor/commands/talk.py
jaeger/actor/commands/testing.py
jaeger/actor/commands/unwind.py
jaeger/actor/commands/version.py
jaeger/commands/__init__.py
jaeger/commands/base.py
jaeger/commands/bootloader.py
jaeger/commands/calibration.py
jaeger/commands/goto.py
jaeger/commands/status.py
jaeger/commands/trajectory.py
jaeger/etc/chiller_APO.yaml
jaeger/etc/chiller_APO_variables.csv
jaeger/etc/fvc.yaml
jaeger/etc/ieb_APO.yaml
jaeger/etc/ieb_LCO.yaml
jaeger/etc/jaeger_APO.yml
jaeger/etc/jaeger_LCO.yml
jaeger/etc/schema.json
jaeger/etc/sextants/epfl.yaml
jaeger/etc/sextants/ieb_sextant.yaml
jaeger/etc/sextants/jaeger_sextant.yml
jaeger/etc/sextants/osu.yaml
jaeger/etc/sextants/schema.json
jaeger/etc/sextants/uw.yaml
jaeger/interfaces/__init__.py
jaeger/interfaces/bus.py
jaeger/interfaces/cannet.py
jaeger/interfaces/message.py
jaeger/interfaces/notifier.py
jaeger/interfaces/virtual.py
jaeger/target/__init__.py
jaeger/target/assignment.py
jaeger/target/configuration.py
jaeger/target/coordinates.py
jaeger/target/design.py
jaeger/target/schemas.py
jaeger/target/too.py
jaeger/target/tools.py
jaeger/utils/__init__.py
jaeger/utils/database.py
jaeger/utils/helpers.py
jaeger/utils/utils.py
jaeger-1.11.0.dist-info/METADATA
jaeger-1.11.0.dist-info/WHEEL
jaeger-1.11.0.dist-info/entry_points.txt
jaeger-1.11.0.dist-info/licenses/LICENSE.md
jaeger-1.11.0.dist-info/RECORD
