Metadata-Version: 2.4
Name: jaeger
Version: 1.11.0
Summary: Controllers for the SDSS-V FPS
Project-URL: Homepage, https://github.com/sdss/jaeger
Project-URL: Repository, https://github.com/sdss/jaeger
Project-URL: Documentation, https://sdss-jaeger.readthedocs.io/en/latest/
Author-email: José Sánchez-Gallego <gallegoj@uw.edu>
License: BSD-3-Clause
License-File: LICENSE.md
Requires-Python: <3.11,>=3.10
Requires-Dist: adbc-driver-postgresql>=0.9.0
Requires-Dist: click-default-group>=1.2.2
Requires-Dist: nptyping>=2.5.0
Requires-Dist: numpy<2,>=1.26.0
Requires-Dist: polars>=1.0.0
Requires-Dist: pyarrow<21.0.0
Requires-Dist: pymodbus<3.8,>=3.7
Requires-Dist: sdss-clu>=2.5.3
Requires-Dist: sdss-coordio>=1.18.1
Requires-Dist: sdss-drift>=1.0.0
Requires-Dist: sdss-kaiju==1.4.0b1; python_version >= '3.11'
Requires-Dist: sdss-kaiju>=1.4.0; python_version >= '3.10' and python_version < '3.11'
Requires-Dist: sdssdb>=0.11.3
Requires-Dist: sdsstools>=1.7.1
Requires-Dist: zc-lockfile>=2.0
